zynk_lite/__about__.py
zynk_lite/__init__.py
zynk_lite/cli.py
zynk_lite/compiler.py
zynk_lite/cynk_cli.py
zynk_lite/errors.py
zynk_lite/interpreter.py
zynk_lite/test_trans.py
zynk_lite/tokens.py
zynk_lite/transpiler.py
zynk_lite/ast/__init__.py
zynk_lite/ast/eval.py
zynk_lite/ast/expressions.py
zynk_lite/ast/parser.py
zynk_lite/ast/zenv.py
zynk_lite/bytecode/__init__.py
zynk_lite/c_base/__init__.py
zynk_lite/c_base/funcs.py
zynk_lite/c_base/initialize.py
zynk_lite/c_base/mem.py
zynk_lite/c_base/stack.py
zynk_lite/c_base/templates.py
zynk_lite/c_base/translator.py
zynk_lite/frontend/__init__.py
zynk_lite/frontend/lexer.py
zynk_lite/native_funcs/__init__.py
zynk_lite/native_funcs/core.py
zynk_lite-0.3.2.dist-info/METADATA
zynk_lite-0.3.2.dist-info/WHEEL
zynk_lite-0.3.2.dist-info/entry_points.txt
zynk_lite-0.3.2.dist-info/licenses/LICENSE.txt
zynk_lite-0.3.2.dist-info/RECORD
