Metadata-Version: 2.4
Name: zynk-lite
Version: 0.3.2
Summary: A programming language
Project-URL: Documentation, https://github.com/Guille-ux/ZynkLite#readme
Project-URL: Issues, https://github.com/Guille-ux/ZynkLite/issues
Project-URL: Source, https://github.com/Guille-ux/ZynkLite
Author-email: Guille <guilleleiratemes@gmail.com>
License: GNU GENERAL PUBLIC LICENSE
License-File: LICENSE.txt
Classifier: Development Status :: 4 - Beta
Classifier: Programming Language :: Python
Classifier: Programming Language :: Python :: 3.8
Classifier: Programming Language :: Python :: 3.9
Classifier: Programming Language :: Python :: 3.10
Classifier: Programming Language :: Python :: 3.11
Classifier: Programming Language :: Python :: 3.12
Classifier: Programming Language :: Python :: Implementation :: CPython
Classifier: Programming Language :: Python :: Implementation :: PyPy
Requires-Python: >=3.6
